nftlabs/__init__.py
tests/__init__.py
tests/test_bundle.py
tests/test_import.py
tests/test_market.py
tests/test_roles.py
tests/test_storage.py
tests/constants/__init__.py
thirdweb/__init__.py
thirdweb/sdk.py
thirdweb/abi/__init__.py
thirdweb/abi/coin/__init__.py
thirdweb/abi/erc1155/__init__.py
thirdweb/abi/erc165/__init__.py
thirdweb/abi/erc20/__init__.py
thirdweb/abi/market/__init__.py
thirdweb/abi/nft/__init__.py
thirdweb/abi/nft_collection/__init__.py
thirdweb/abi/pack/__init__.py
thirdweb/constants/__init__.py
thirdweb/constants/erc_interfaces.py
thirdweb/errors/__init__.py
thirdweb/modules/__init__.py
thirdweb/modules/base.py
thirdweb/modules/bundle.py
thirdweb/modules/currency.py
thirdweb/modules/market.py
thirdweb/modules/nft.py
thirdweb/modules/nft_types.py
thirdweb/modules/pack.py
thirdweb/modules/collection/__init__.py
thirdweb/options/__init__.py
thirdweb/options/sdk_options.py
thirdweb/storage/__init__.py
thirdweb/storage/ipfs_storage.py
thirdweb/storage/util.py
thirdweb/types/__init__.py
thirdweb/types/listing.py
thirdweb/types/role.py
thirdweb/types/bundle/__init__.py
thirdweb/types/collection/__init__.py
thirdweb/types/collection/types.py
thirdweb/types/currency/__init__.py
thirdweb/types/market/__init__.py
thirdweb/types/metadata/__init__.py
thirdweb/types/modules/__init__.py
thirdweb/types/nft/__init__.py
thirdweb/types/pack/__init__.py
nftlabs_sdk-0.4.0.dist-info/METADATA
nftlabs_sdk-0.4.0.dist-info/WHEEL
nftlabs_sdk-0.4.0.dist-info/top_level.txt
nftlabs_sdk-0.4.0.dist-info/RECORD
