Metadata-Version: 2.1
Name: nftlabs-sdk
Version: 0.4.0
Summary: Official Thirdweb sdk
Home-page: https://github.com/nftlabs/nftlabs-sdk-python
Author: NFTLabs
Author-email: sdk@thirdweb.com
License: MIT
Platform: UNKNOWN
Classifier: License :: OSI Approved :: MIT License
Classifier: Programming Language :: Python :: 3
Classifier: Programming Language :: Python :: 3.6
Requires-Dist: dataclasses-json
Requires-Dist: thirdweb-web3
Requires-Dist: requests
Requires-Dist: thirdweb-contract-wrappers
Requires-Dist: web3
